pytsviz/__init__.py
pytsviz/utils.py
pytsviz/viz.py
pytsviz-0.1.0.dist-info/LICENSE
pytsviz-0.1.0.dist-info/WHEEL
pytsviz-0.1.0.dist-info/METADATA
pytsviz-0.1.0.dist-info/RECORD
