Metadata-Version: 2.1
Name: pytsviz
Version: 0.1.0
Summary: A suite of tools to quickly analyze and visualize time series data.
Home-page: https://github.com/xtreamsrl/pytsviz
License: MIT
Keywords: python,data visualization,time series,data science
Author: xtream
Author-email: oss@xtreamers.io
Maintainer: xtream
Maintainer-email: oss@xtreamers.io
Requires-Python: >=3.8,<4.0
Classifier: License :: OSI Approved :: MIT License
Classifier: Programming Language :: Python :: 3
Classifier: Programming Language :: Python :: 3.10
Classifier: Programming Language :: Python :: 3.8
Classifier: Programming Language :: Python :: 3.9
Requires-Dist: colour (>=0.1.5,<0.2.0)
Requires-Dist: numpy (>=1.18.5,<2.0.0)
Requires-Dist: pandas (>=1.0.4,<2.0.0)
Requires-Dist: plotly (>=4.8.1,<5.0.0)
Requires-Dist: scipy (>=1.4.1,<2.0.0)
Requires-Dist: statsmodels (>=0.12.2,<0.13.0)
Project-URL: Bug Tracker, https://github.com/xtreamsrl/pytsviz/issues
Project-URL: Documentation, https://pytsviz.readthedocs.io/en/latest/
Project-URL: Repository, https://github.com/xtreamsrl/pytsviz
